logging_json_formatter/__init__.py
logging_json_formatter/formatters.py
python_logging_json_formatter-0.1.0.dist-info/DESCRIPTION.rst
python_logging_json_formatter-0.1.0.dist-info/METADATA
python_logging_json_formatter-0.1.0.dist-info/RECORD
python_logging_json_formatter-0.1.0.dist-info/WHEEL
python_logging_json_formatter-0.1.0.dist-info/metadata.json
python_logging_json_formatter-0.1.0.dist-info/top_level.txt
