Metadata-Version: 2.0
Name: python-logging-json-formatter
Version: 0.1.0
Summary: A logging formatter that appends extra data as JSON, e.g. for loggly
Home-page: https://github.com/opbeat/python-logging-json-formatter
Author: Opbeat, Inc
Author-email: support@opbeat.com
License: BSD
Keywords: logging,json,loggly
Platform: UNKNOWN
Classifier: Development Status :: 2 - Pre-Alpha
Classifier: Intended Audience :: Developers
Classifier: License :: OSI Approved :: BSD License
Classifier: Natural Language :: English
Classifier: Programming Language :: Python :: 2
Classifier: Programming Language :: Python :: 2.7
Classifier: Programming Language :: Python :: 3
Classifier: Programming Language :: Python :: 3.3
Classifier: Programming Language :: Python :: 3.4
Classifier: Programming Language :: Python :: 3.5
